MANIFEST.in
README.md
build.py
pyproject.toml
requirements-dev.txt
requirements.txt
setup.py
sockets_communication/bluetooth.py
sockets_communication/client.py
sockets_communication/communication.py
sockets_communication/exceptions.py
sockets_communication/process.py
sockets_communication/server.py
sockets_communication/service.py
sockets_communication.egg-info/PKG-INFO
sockets_communication.egg-info/SOURCES.txt
sockets_communication.egg-info/dependency_links.txt
sockets_communication.egg-info/requires.txt
sockets_communication.egg-info/top_level.txt