Metadata-Version: 2.1
Name: sockets-communication
Version: 1.4.2
Summary: This module provides a wrapper for the built-in socket module in python. The program provides server and. client classes, with the communication methods.
Home-page: https://github.com/Shahaf-F-S/sockets-communication
Author: Shahaf Frank-Shapir
Author-email: shahaffrs@gmail.com
License: MIT
Classifier: Intended Audience :: Developers
Classifier: License :: OSI Approved :: MIT License
Classifier: Programming Language :: Python
Classifier: Programming Language :: Python :: 3
Classifier: Programming Language :: Python :: 3.8
Classifier: Programming Language :: Python :: 3.9
Classifier: Programming Language :: Python :: 3.10
Classifier: Programming Language :: Python :: 3.11
Classifier: Operating System :: OS Independent
Provides-Extra: dev
